[
  {
    "id": "f4527b6f-2593-4246-90a5-772be7d78938",
    "userId": "0374e29e-d6a8-4e93-9ebc-6d31d1a398b2",
    "name": "شركة اختبار mp1g7nh4",
    "nameEn": "",
    "businessName": "شركة اختبار mp1g7nh4",
    "businessType": "company",
    "description": "شركة اختبار للمعادن والسكراب",
    "email": "supplier-mp1g7nh4@test.sheikha.local",
    "phone": null,
    "website": null,
    "whatsapp": null,
    "country": "SA",
    "city": "الرياض",
    "region": null,
    "address": null,
    "categories": [
      "iron",
      "copper"
    ],
    "specializations": [],
    "verified": false,
    "verificationDate": null,
    "commercialRegistration": null,
    "vatNumber": null,
    "sharia": {
      "compliant": true,
      "noRiba": true,
      "audited": false
    },
    "stats": {
      "totalProducts": 0,
      "activeProducts": 0,
      "totalOrders": 0,
      "completedOrders": 0,
      "totalRevenue": 0,
      "rating": {
        "average": 0,
        "count": 0
      }
    },
    "status": "active",
    "featured": false,
    "documents": [],
    "logo": null,
    "createdAt": "2026-05-11T17:01:05.653Z",
    "updatedAt": "2026-05-11T17:01:05.653Z"
  }
]