[
  {
    "id": "patent-94371c879913ad9b",
    "titleAr": "طريقة جديدة لتحسين الخلايا الشمسية بالكمية",
    "titleEn": "Novel Quantum Enhancement for Photovoltaic Cells",
    "domainId": "clean_energy",
    "inventors": [
      "سلمان أحمد بن سلمان الراجح"
    ],
    "abstract": "",
    "filingDate": "2026-04-12T15:40:45.308Z",
    "status": "filed",
    "projectId": "proj-fd931f8fb5b3f036",
    "registeredAt": "2026-04-12T15:40:45.308Z",
    "updatedAt": "2026-04-12T15:40:45.308Z",
    "sheikhaRef": "SH-PAT-MNVXKMT9"
  },
  {
    "id": "patent-1fed91ad237d6083",
    "titleAr": "طريقة جديدة لتحسين الخلايا الشمسية بالكمية",
    "titleEn": "Novel Quantum Enhancement for Photovoltaic Cells",
    "domainId": "clean_energy",
    "inventors": [
      "سلمان أحمد بن سلمان الراجح"
    ],
    "abstract": "",
    "filingDate": "2026-04-12T15:41:53.593Z",
    "status": "filed",
    "projectId": "proj-5d602e5451c79d9f",
    "registeredAt": "2026-04-12T15:41:53.593Z",
    "updatedAt": "2026-04-12T15:41:53.593Z",
    "sheikhaRef": "SH-PAT-MNVXM3I1"
  }
]